Metadata-Version: 2.1
Name: slash-cog
Version: 0.0.3
Summary: A drop-in vanilla discord.py cog to add slash command support with little to no code modifications
Home-page: https://github.com/CortexPE/slash_cog
Author: CortexPE
License: MIT
Platform: UNKNOWN
Classifier: Development Status :: 1 - Planning
Classifier: Framework :: AsyncIO
Classifier: Intended Audience :: Developers
Classifier: License :: OSI Approved :: MIT License
Classifier: Operating System :: OS Independent
Classifier: Programming Language :: Python :: 3.6
Classifier: Programming Language :: Python :: 3.7
Classifier: Programming Language :: Python :: 3.8
Classifier: Programming Language :: Python :: 3.9
Classifier: Topic :: Communications :: Chat
Classifier: Topic :: Internet
Classifier: Typing :: Typed
Requires-Python: >=3.6
